waybill/__init__.py
waybill/cli.py
waybill-0.1.3.dist-info/DESCRIPTION.rst
waybill-0.1.3.dist-info/entry_points.txt
waybill-0.1.3.dist-info/LICENSE.txt
waybill-0.1.3.dist-info/METADATA
waybill-0.1.3.dist-info/metadata.json
waybill-0.1.3.dist-info/pbr.json
waybill-0.1.3.dist-info/RECORD
waybill-0.1.3.dist-info/top_level.txt
waybill-0.1.3.dist-info/WHEEL
