Metadata-Version: 2.0
Name: waybill
Version: 0.1.3
Summary: A python commandline tool to run commandline tools that are in docker images
Home-page: http://github.com/rocktavious/waybill
Author: Kyle Rockman
Author-email: ['kyle.rockman@mac.com']
License: UNKNOWN
Platform: UNKNOWN
Requires-Dist: battalion (>=0.2.1)
